python_build_utils/__init__.py
python_build_utils/clean_pyd_modules.py
python_build_utils/cli_logger.py
python_build_utils/cli_tools.py
python_build_utils/collect_dep_modules.py
python_build_utils/collect_pyd_modules.py
python_build_utils/constants.py
python_build_utils/cythonized_setup.py
python_build_utils/exceptions.py
python_build_utils/pyd2wheel.py
python_build_utils/remove_tarballs.py
python_build_utils/rename_wheel_files.py
python_build_utils-0.3.5.dist-info/licenses/LICENSE
python_build_utils-0.3.5.dist-info/METADATA
python_build_utils-0.3.5.dist-info/WHEEL
python_build_utils-0.3.5.dist-info/entry_points.txt
python_build_utils-0.3.5.dist-info/top_level.txt
python_build_utils-0.3.5.dist-info/RECORD
