Metadata-Version: 2.4
Name: python-build-utils
Version: 0.3.5
Summary: Small collection of command line utilities to assist with building your python wheels
Author-email: Eelco van Vliet <eelco@davelab.nl>
Project-URL: Repository, https://github.com/dave-Lab-and-Engineering/python-build-utils
Keywords: python
Classifier: Intended Audience :: Developers
Classifier: Programming Language :: Python
Classifier: Programming Language :: Python :: 3
Classifier: Programming Language :: Python :: 3.10
Classifier: Programming Language :: Python :: 3.11
Classifier: Programming Language :: Python :: 3.12
Classifier: Programming Language :: Python :: 3.13
Classifier: Topic :: Software Development :: Libraries :: Python Modules
Requires-Python: <4.0,>=3.10
License-File: LICENSE
Requires-Dist: click>=8.1.8
Requires-Dist: rich>=13.9.4
Provides-Extra: all
Requires-Dist: pipdeptree>=2.26.0; extra == "all"
Requires-Dist: setuptools>=79.0.0; extra == "all"
Requires-Dist: cython>=3.0.12; extra == "all"
Provides-Extra: dep
Requires-Dist: pipdeptree>=2.26.0; extra == "dep"
Provides-Extra: setup
Requires-Dist: setuptools>=79.0.0; extra == "setup"
Requires-Dist: cython>=3.0.12; extra == "setup"
Dynamic: license-file
